architecture/__init__.py
architecture/cruise-storage-architecture.excalidraw
architecture/cruise-storage-architecture.png
architecture/cruise-storage-architecture.svg
docs/.DS_Store
docs/Makefile
docs/build/.DS_Store
docs/build/doctrees/architecture.doctree
docs/build/doctrees/environment.pickle
docs/build/doctrees/index.doctree
docs/build/doctrees/jz_python_chest.doctree
docs/build/doctrees/leetcode.doctree
docs/build/doctrees/modules.doctree
docs/build/doctrees/python_lib_examples.doctree
docs/build/doctrees/pytorch_tutorials.doctree
docs/build/html/.buildinfo
docs/build/html/_modules/index.html
docs/build/html/_modules/jz_python_chest/aiofiles_example.html
docs/build/html/_modules/jz_python_chest/aiofiles_yield.html
docs/build/html/_modules/jz_python_chest/aiohttp_example.html
docs/build/html/_modules/jz_python_chest/callback_example.html
docs/build/html/_modules/jz_python_chest/remove_empty_lines_example.html
docs/build/html/_modules/leetcode/1920.html
docs/build/html/_modules/logging.html
docs/build/html/_modules/python_lib_examples/args.html
docs/build/html/_modules/python_lib_examples/async_files.html
docs/build/html/_modules/python_lib_examples/asyncio_example.html
docs/build/html/_modules/python_lib_examples/binary_search.html
docs/build/html/_modules/python_lib_examples/binary_tree.html
docs/build/html/_modules/python_lib_examples/bisect_example.html
docs/build/html/_modules/python_lib_examples/built_in_args.html
docs/build/html/_modules/python_lib_examples/built_in_list_dict_str.html
docs/build/html/_modules/python_lib_examples/built_in_yield.html
docs/build/html/_modules/python_lib_examples/functools_lrucache.html
docs/build/html/_modules/python_lib_examples/logger_example.html
docs/build/html/_modules/python_lib_examples/multiprocess_test.html
docs/build/html/_modules/python_lib_examples/ordered_dict_lru_cache.html
docs/build/html/_modules/python_lib_examples/pool_deadlock.html
docs/build/html/_modules/python_lib_examples/shared_memory_example.html
jz_python_chest-0.1.7.dist-info/METADATA
jz_python_chest-0.1.7.dist-info/WHEEL
jz_python_chest-0.1.7.dist-info/RECORD
